{
  "disabledtooltip": [],
  "currentlyFocusedSackNumber": 0,
  "currentlySelectedSackNumber": 0,
  "sacks": [
    {
      "iconinfo": null,
      "items": [
        {
          "stackSize": 1,
          "seed": 12977,
          "baseName": "Records\\Item\\EquipmentWeapon\\Spear\\US_N_BabylonianRaiment.dbr",
          "prefixName": "",
          "suffixName": "",
          "relicName": "",
          "relicBonus": "",
          "var1": 0,
          "relicName2": "",
          "relicBonus2": "",
          "var2": 2035248,
          "pointX": 0,
          "pointY": 0
        },
        {
          "stackSize": 1,
          "seed": 326,
          "baseName": "Records\\Item\\EquipmentWeapon\\Sword\\U_N_SoulCarver.dbr",
          "prefixName": "",
          "suffixName": "",
          "relicName": "",
          "relicBonus": "",
          "var1": 0,
          "relicName2": "",
          "relicBonus2": "",
          "var2": 2035248,
          "pointX": 1,
          "pointY": 0
        },
        {
          "stackSize": 1,
          "seed": 25345,
          "baseName": "Records\\Item\\EquipmentWeapon\\Axe\\US_N_ObsidianArmor.dbr",
          "prefixName": "",
          "suffixName": "",
          "relicName": "",
          "relicBonus": "",
          "var1": 0,
          "relicName2": "",
          "relicBonus2": "",
          "var2": 2035248,
          "pointX": 2,
          "pointY": 0
        },
        {
          "stackSize": 1,
          "seed": 3392,
          "baseName": "Records\\Item\\EquipmentArmor\\US_N_ObsidianArmor.dbr",
          "prefixName": "",
          "suffixName": "",
          "relicName": "",
          "relicBonus": "",
          "var1": 0,
          "relicName2": "",
          "relicBonus2": "",
          "var2": 2035248,
          "pointX": 4,
          "pointY": 0
        },
        {
          "stackSize": 1,
          "seed": 22839,
          "baseName": "Records\\Item\\EquipmentWeapon\\Sword\\U_N_Marduk'sRage.dbr",
          "prefixName": "",
          "suffixName": "",
          "relicName": "",
          "relicBonus": "",
          "var1": 0,
          "relicName2": "",
          "relicBonus2": "",
          "var2": 2035248,
          "pointX": 6,
          "pointY": 0
        },
        {
          "stackSize": 1,
          "seed": 19670,
          "baseName": "Records\\Item\\EquipmentShield\\US_N_LabyrinthineArmor.dbr",
          "prefixName": "",
          "suffixName": "",
          "relicName": "",
          "relicBonus": "",
          "var1": 0,
          "relicName2": "",
          "relicBonus2": "",
          "var2": 2035248,
          "pointX": 7,
          "pointY": 0
        },
        {
          "stackSize": 1,
          "seed": 16679,
          "baseName": "Records\\Item\\EquipmentShield\\U_N_Stonewall.dbr",
          "prefixName": "",
          "suffixName": "",
          "relicName": "",
          "relicBonus": "",
          "var1": 0,
          "relicName2": "",
          "relicBonus2": "",
          "var2": 2035248,
          "pointX": 9,
          "pointY": 0
        },
        {
          "stackSize": 1,
          "seed": 2716,
          "baseName": "Records\\Item\\EquipmentHelm\\US_N_ObsidianArmor.dbr",
          "prefixName": "",
          "suffixName": "",
          "relicName": "",
          "relicBonus": "",
          "var1": 0,
          "relicName2": "",
          "relicBonus2": "",
          "var2": 2035248,
          "pointX": 11,
          "pointY": 0
        },
        {
          "stackSize": 1,
          "seed": 27852,
          "baseName": "Records\\Item\\EquipmentArmband\\C06_Armband04.dbr",
          "prefixName": "Records\\Item\\LootMagicalAffixes\\Prefix\\Default\\Rare_StrLife_02.dbr",
          "suffixName": "Records\\Item\\LootMagicalAffixes\\Suffix\\Default\\Rare_Guile_01.dbr",
          "relicName": "",
          "relicBonus": "",
          "var1": 0,
          "relicName2": "",
          "relicBonus2": "",
          "var2": 2035248,
          "pointX": 13,
          "pointY": 0
        },
        {
          "stackSize": 1,
          "seed": 1532,
          "baseName": "Records\\Item\\EquipmentArmband\\US_N_ObsidianArmor.dbr",
          "prefixName": "",
          "suffixName": "",
          "relicName": "",
          "relicBonus": "",
          "var1": 0,
          "relicName2": "",
          "relicBonus2": "",
          "var2": 2035248,
          "pointX": 15,
          "pointY": 0
        },
        {
          "stackSize": 1,
          "seed": 2518,
          "baseName": "Records\\Item\\EquipmentGreaves\\US_N_GebelTjauti.dbr",
          "prefixName": "",
          "suffixName": "",
          "relicName": "",
          "relicBonus": "",
          "var1": 0,
          "relicName2": "",
          "relicBonus2": "",
          "var2": 2035248,
          "pointX": 7,
          "pointY": 2
        },
        {
          "stackSize": 1,
          "seed": 22917,
          "baseName": "Records\\Item\\EquipmentGreaves\\U_N_ArdentGreaves.dbr",
          "prefixName": "",
          "suffixName": "",
          "relicName": "",
          "relicBonus": "",
          "var1": 0,
          "relicName2": "",
          "relicBonus2": "",
          "var2": 2035248,
          "pointX": 11,
          "pointY": 2
        },
        {
          "stackSize": 1,
          "seed": 27329,
          "baseName": "Records\\Item\\Relics\\01_Act1_DionysusWineskin.dbr",
          "prefixName": "",
          "suffixName": "",
          "relicName": "",
          "relicBonus": "records\\item\\lootmagicalaffixes\\animalrelics\\bonuses\\defensive_bleedresist_01.dbr",
          "var1": 3,
          "relicName2": "",
          "relicBonus2": "",
          "var2": 2035248,
          "pointX": 17,
          "pointY": 0
        },
        {
          "stackSize": 1,
          "seed": 14748,
          "baseName": "Records\\Item\\EquipmentRing\\C04_Ring01.dbr",
          "prefixName": "Records\\Item\\LootMagicalAffixes\\Prefix\\Default\\Rare_StrLife_03.dbr",
          "suffixName": "Records\\Item\\LootMagicalAffixes\\Suffix\\Default\\Character_AttributeStrength_02.dbr",
          "relicName": "",
          "relicBonus": "",
          "var1": 0,
          "relicName2": "",
          "relicBonus2": "",
          "var2": 2035248,
          "pointX": 17,
          "pointY": 1
        },
        {
          "stackSize": 1,
          "seed": 3658,
          "baseName": "Records\\Item\\EquipmentGreaves\\US_N_ObsidianArmor.dbr",
          "prefixName": "",
          "suffixName": "",
          "relicName": "",
          "relicBonus": "",
          "var1": 0,
          "relicName2": "",
          "relicBonus2": "",
          "var2": 2035248,
          "pointX": 9,
          "pointY": 2
        },
        {
          "stackSize": 1,
          "seed": 23449,
          "baseName": "Records\\Item\\EquipmentArmor\\US_N_Ramses'RoyalArmor.dbr",
          "prefixName": "",
          "suffixName": "",
          "relicName": "",
          "relicBonus": "",
          "var1": 0,
          "relicName2": "",
          "relicBonus2": "",
          "var2": 1065353216,
          "pointX": 4,
          "pointY": 3
        },
        {
          "stackSize": 1,
          "seed": 25139,
          "baseName": "Records\\Item\\EquipmentWeapon\\Club\\US_N_Ramses'RoyalArmor.dbr",
          "prefixName": "",
          "suffixName": "",
          "relicName": "",
          "relicBonus": "",
          "var1": 0,
          "relicName2": "",
          "relicBonus2": "",
          "var2": 1773662272,
          "pointX": 6,
          "pointY": 4
        },
        {
          "stackSize": 1,
          "seed": 32305,
          "baseName": "Records\\Item\\EquipmentArmband\\U_N_BracersofAtlas.dbr",
          "prefixName": "",
          "suffixName": "",
          "relicName": "",
          "relicBonus": "",
          "var1": 0,
          "relicName2": "",
          "relicBonus2": "",
          "var2": 1065353216,
          "pointX": 11,
          "pointY": 7
        },
        {
          "stackSize": 1,
          "seed": 9839,
          "baseName": "Records\\Item\\EquipmentGreaves\\US_N_GebelTjauti.dbr",
          "prefixName": "",
          "suffixName": "",
          "relicName": "",
          "relicBonus": "",
          "var1": 0,
          "relicName2": "",
          "relicBonus2": "",
          "var2": 1065353216,
          "pointX": 10,
          "pointY": 4
        },
        {
          "stackSize": 1,
          "seed": 26625,
          "baseName": "Records\\Item\\EquipmentShield\\U_N_Thutmose'Buckler.dbr",
          "prefixName": "",
          "suffixName": "",
          "relicName": "",
          "relicBonus": "",
          "var1": 0,
          "relicName2": "",
          "relicBonus2": "",
          "var2": 1065353216,
          "pointX": 14,
          "pointY": 5
        },
        {
          "stackSize": 1,
          "seed": 15089,
          "baseName": "Records\\Item\\EquipmentArmband\\US_N_ThebanPanoply.dbr",
          "prefixName": "",
          "suffixName": "",
          "relicName": "",
          "relicBonus": "",
          "var1": 0,
          "relicName2": "",
          "relicBonus2": "",
          "var2": 1065353216,
          "pointX": 15,
          "pointY": 9
        },
        {
          "stackSize": 1,
          "seed": 24018,
          "baseName": "records\\xpack2\\item\\equipmentweapons\\1hranged\\u_n_04.dbr",
          "prefixName": "",
          "suffixName": "",
          "relicName": "",
          "relicBonus": "",
          "var1": 0,
          "relicName2": "",
          "relicBonus2": "",
          "var2": 1065353216,
          "pointX": 10,
          "pointY": 12
        },
        {
          "stackSize": 1,
          "seed": 8068,
          "baseName": "Records\\Item\\EquipmentAmulet\\U_N_ElectrumCharm.dbr",
          "prefixName": "",
          "suffixName": "",
          "relicName": "",
          "relicBonus": "",
          "var1": 0,
          "relicName2": "",
          "relicBonus2": "",
          "var2": 1065353216,
          "pointX": 12,
          "pointY": 14
        },
        {
          "stackSize": 1,
          "seed": 1085,
          "baseName": "Records\\Item\\EquipmentWeapon\\Spear\\U_N_TheEviscerator.dbr",
          "prefixName": "",
          "suffixName": "",
          "relicName": "",
          "relicBonus": "",
          "var1": 0,
          "relicName2": "",
          "relicBonus2": "",
          "var2": 1065353216,
          "pointX": 14,
          "pointY": 13
        }
      ]
    },
    {
      "iconinfo": null,
      "items": []
    },
    {
      "iconinfo": null,
      "items": []
    },
    {
      "iconinfo": null,
      "items": []
    },
    {
      "iconinfo": null,
      "items": []
    },
    {
      "iconinfo": null,
      "items": []
    },
    {
      "iconinfo": null,
      "items": []
    },
    {
      "iconinfo": null,
      "items": []
    },
    {
      "iconinfo": null,
      "items": []
    },
    {
      "iconinfo": null,
      "items": []
    },
    {
      "iconinfo": null,
      "items": []
    },
    {
      "iconinfo": null,
      "items": []
    }
  ]
}